Workbook

Sheet all-data
B1: Quandl Code | C1: Indicator Name | D1: Country Name | E1: Country Code | F1: Indicator Code | G1: Start Date | H1: Frequency
B2: AFGBOT | C2: Balance of Trade | D2: Afghanistan | E2: AFG | F2: BOT | G2: 37711 | H2: Yearly
B3: AFGCA | C3: Current Account | D3: Afghanistan | E3: AFG | F3: CA | G3: 37711 | H3: Yearly
B4: AFGCAGDP | C4: Current Account to GDP | D4: Afghanistan | E4: AFG | F4: CAGDP | G4: 37711 | H4: Yearly
B5: AFGCPIC | C5: Inflation Rate | D5: Afghanistan | E5: AFG | F5: CPIC | G5: 38442 | H5: Monthly
B6: AFGCTR | C6: Corporate Tax Rate | D6: Afghanistan | E6: AFG | F6: CTR | G6: 38718 | H6: Yearly
B7: AFGEXVOL | C7: Exports | D7: Afghanistan | E7: AFG | F7: EXVOL | G7: 36616 | H7: Yearly
B8: AFGG | C8: GDP | D8: Afghanistan | E8: AFG | F8: G | G8: 22281 | H8: Yearly
B9: AFGGAGR | C9: GDP Annual Growth Rate | D9: Afghanistan | E9: AFG | F9: GAGR | G9: 37711 | H9: Yearly
B10: AFGGBGT | C10: Government Budget | D10: Afghanistan | E10: AFG | F10: GBGT | G10: 38807 | H10: Yearly
B11: AFGGDG | C11: Government Debt to GDP | D11: Afghanistan | E11: AFG | F11: GDG | G11: 38807 | H11: Yearly
B12: AFGGOLD | C12: Gold Reserves | D12: Afghanistan | E12: AFG | F12: GOLD | G12: 39721 | H12: Quarterly
B13: AFGGPC | C13: GDP per capita | D13: Afghanistan | E13: AFG | F13: GPC | G13: 22281 | H13: Yearly
... B20: AFGUNR | C20: Unemployment Rate | D20: Afghanistan | E20: AFG | F20: UNR | G20: 33603 | H20: Yearly
B21: AFGCUR | C21: =INDEX('list-indicators'!$A$2:$A$293, MATCH(F21,'list-indicators'!$B$2:$B$293,0)) -> Currency Exchange Rate | D21: =INDEX('list-countries'!$B$2:$B$203,MATCH(E21,'list-countries'!$C$2:$C$203,0)) -> Afghanistan | E21: =LEFT(B21,3) -> AFG | F21: =RIGHT(B21,LEN(B21)-3) -> CUR | G21: 40779 | H21: Daily
B22: ALBBCONF | C22: Business Confidence | D22: Albania | E22: ALB | F22: BCONF | G22: 37437 | H22: Quarterly
B23: ALBBOT | C23: Balance of Trade | D23: Albania | E23: ALB | F23: BOT | G23: 33984 | H23: Monthly
B24: ALBCA | C24: Current Account | D24: Albania | E24: ALB | F24: CA | G24: 33984 | H24: Monthly
B25: ALBCAGDP | C25: Current Account to GDP | D25: Albania | E25: ALB | F25: CAGDP | G25: 29586 | H25: Yearly
B26: ALBCF | C26: Capital Flows | D26: Albania | E26: ALB | F26: CF | G26: 38001 | H26: Monthly
B27: ALBCNCN | C27: Consumer Confidence | D27: Albania | E27: ALB | F27: CNCN | G27: 37802 | H27: Quarterly
B28: ALBCPI | C28: Consumer Price Index (CPI) | D28: Albania | E28: ALB | F28: CPI | G28: 38732 | H28: Monthly
B29: ALBCPIC | C29: Inflation Rate | D29: Albania | E29: ALB | F29: CPIC | G29: 34730 | H29: Monthly
B30: ALBCPICM | C30: Inflation Rate MoM | D30: Albania | E30: ALB | F30: CPICM | G30: 38763 | H30: Monthly
B31: ALBCSP | C31: Consumer Spending | D31: Albania | E31: ALB | F31: CSP | G31: 35246 | H31: Yearly
B32: ALBCTR | C32: Corporate Tax Rate | D32: Albania | E32: ALB | F32: CTR | G32: 38718 | H32: Yearly
B33: ALBDINV | C33: Changes in Inventories | D33: Albania | E33: ALB | F33: DINV | G33: 35246 | H33: Yearly
... B64: ALBWAGE | C64: Average Monthly Wages | D64: Albania | E64: ALB | F64: WAGE | G64: 34288 | H64: Quarterly
B65: ALBCUR | C65: =INDEX('list-indicators'!$A$2:$A$293, MATCH(F65,'list-indicators'!$B$2:$B$293,0)) -> Currency Exchange Rate | D65: =INDEX('list-countries'!$B$2:$B$203,MATCH(E65,'list-countries'!$C$2:$C$203,0)) -> Albania | E65: =LEFT(B65,3) -> ALB | F65: =RIGHT(B65,LEN(B65)-3) -> CUR | G65: 40779 | H65: Daily
B66: DZABOT | C66: Balance of Trade | D66: Algeria | E66: DZA | F66: BOT | G66: 33785 | H66: Monthly
B67: DZACA | C67: Current Account | D67: Algeria | E67: DZA | F67: CA | G67: 33969 | H67: Quarterly
B68: DZACAGDP | C68: Current Account to GDP | D68: Algeria | E68: DZA | F68: CAGDP | G68: 29586 | H68: Yearly
B69: DZACPIC | C69: Inflation Rate | D69: Algeria | E69: DZA | F69: CPIC | G69: 37256 | H69: Monthly
B70: DZACSP | C70: Consumer Spending | D70: Algeria | E70: DZA | F70: CSP | G70: 34880 | H70: Yearly
B71: DZACTR | C71: Corporate Tax Rate | D71: Algeria | E71: DZA | F71: CTR | G71: 40909 | H71: Yearly
B72: DZADINV | C72: Changes in Inventories | D72: Algeria | E72: DZA | F72: DINV | G72: 34880 | H72: Yearly
B73: DZAEXVOL | C73: Exports | D73: Algeria | E73: DZA | F73: EXVOL | G73: 33785 | H73: Monthly
B74: DZAFINF | C74: Food Inflation | D74: Algeria | E74: DZA | F74: FINF | G74: 40466 | H74: Monthly
B75: DZAG | C75: GDP | D75: Algeria | E75: DZA | F75: G | G75: 22281 | H75: Yearly
B76: DZAGAGR | C76: GDP Annual Growth Rate | D76: Algeria | E76: DZA | F76: GAGR | G76: 37256 | H76: Yearly
B77: DZAGBGT | C77: Government Budget | D77: Algeria | E77: DZA | F77: GBGT | G77: 33238 | H77: Yearly
... B95: DZAUNR | C95: Unemployment Rate | D95: Algeria | E95: DZA | F95: UNR | G95: 36433 | H95: Yearly
B96: DZACUR | C96: =INDEX('list-indicators'!$A$2:$A$293, MATCH(F96,'list-indicators'!$B$2:$B$293,0)) -> Currency Exchange Rate | D96: =INDEX('list-countries'!$B$2:$B$203,MATCH(E96,'list-countries'!$C$2:$C$203,0)) -> Algeria | E96: =LEFT(B96,3) -> DZA | F96: =RIGHT(B96,LEN(B96)-3) -> CUR | G96: 40898 | H96: Daily
B97: ANDSTR | C97: Sales Tax Rate | VAT | D97: Andorra | E97: AND | F97: STR | G97: 41275 | H97: Yearly
B98: AGOBCONF | C98: Business Confidence | D98: Angola | E98: AGO | F98: BCONF | G98: 39721 | H98: Quarterly
B99: AGOBOT | C99: Balance of Trade | D99: Angola | E99: AGO | F99: BOT | G99: 37621 | H99: Quarterly
B100: AGOCA | C100: Current Account | D100: Angola | E100: AGO | F100: CA | G100: 36891 | H100: Yearly
B101: AGOCAGDP | C101: Current Account to GDP | D101: Angola | E101: AGO | F101: CAGDP | G101: 29586 | H101: Yearly
B102: AGOCPI | C102: Consumer Price Index (CPI) | D102: Angola | E102: AGO | F102: CPI | G102: 33984 | H102: Monthly
B103: AGOCPIC | C103: Inflation Rate | D103: Angola | E103: AGO | F103: CPIC | G103: 36922 | H103: Monthly
B104: AGOCPICM | C104: Inflation Rate MoM | D104: Angola | E104: AGO | F104: CPICM | G104: 40557 | H104: Monthly
B105: AGOCTR | C105: Corporate Tax Rate | D105: Angola | E105: AGO | F105: CTR | G105: 38718 | H105: Yearly
B106: AGOEXVOL | C106: Exports | D106: Angola | E106: AGO | F106: EXVOL | G106: 37621 | H106: Quarterly
B107: AGOFINF | C107: Food Inflation | D107: Angola | E107: AGO | F107: FINF | G107: 37636 | H107: Monthly
B108: AGOG | C108: GDP | D108: Angola | E108: AGO | F108: G | G108: 31412 | H108: Yearly
... B122: AGOUNR | C122: Unemployment Rate | D122: Angola | E122: AGO | F122: UNR | G122: 38717 | H122: Yearly
B123: AGOCUR | C123: =INDEX('list-indicators'!$A$2:$A$293, MATCH(F123,'list-indicators'!$B$2:$B$293,0)) -> Currency Exchange Rate | D123: =INDEX('list-countries'!$B$2:$B$203,MATCH(E123,'list-countries'!$C$2:$C$203,0)) -> Angola | E123: =LEFT(B123,3) -> AGO | F123: =RIGHT(B123,LEN(B123)-3) -> CUR | G123: 40779 | H123: Daily
B124: ATGG | C124: GDP | D124: Antigua and Barbuda | E124: ATG | F124: G | G124: 28490 | H124: Yearly
B125: ATGGPCP | C125: GDP Per Capita PPP | D125: Antigua and Barbuda | E125: ATG | F125: GPCP | G125: 29586 | H125: Yearly
B126: ATGSTR | C126: Sales Tax Rate | VAT | D126: Antigua and Barbuda | E126: ATG | F126: STR | G126: 41640 | H126: Yearly
B127: ARGBOT | C127: Balance of Trade | D127: Argentina | E127: ARG | F127: BOT | G127: 20835 | H127: Monthly
B128: ARGCA | C128: Current Account | D128: Argentina | E128: ARG | F128: CA | G128: 27805 | H128: Quarterly
B129: ARGCAGDP | C129: Current Account to GDP | D129: Argentina | E129: ARG | F129: CAGDP | G129: 29586 | H129: Yearly
B130: ARGCARS | C130: Domestic Car Sales | D130: Argentina | E130: ARG | F130: CARS | G130: 35079 | H130: Monthly
B131: ARGCF | C131: Capital Flows | D131: Argentina | E131: ARG | F131: CF | G131: 32919 | H131: Quarterly
B132: ARGCNCN | C132: Consumer Confidence | D132: Argentina | E132: ARG | F132: CNCN | G132: 36965 | H132: Monthly
B133: ARGCPI | C133: Consumer Price Index (CPI) | D133: Argentina | E133: ARG | F133: CPI | G133: 18278 | H133: Monthly
B134: ARGCPIC | C134: Inflation Rate | D134: Argentina | E134: ARG | F134: CPIC | G134: 16102 | H134: Monthly
B135: ARGCPICM | C135: Inflation Rate MoM | D135: Argentina | E135: ARG | F135: CPICM | G135: 41654 | H135: Monthly
... B185: ARGWAGE | C185: Wage Index | D185: Argentina | E185: ARG | F185: WAGE | G185: 37179 | H185: Monthly
B186: ARGCUR | C186: =INDEX('list-indicators'!$A$2:$A$293, MATCH(F186,'list-indicators'!$B$2:$B$293,0)) -> Currency Exchange Rate | D186: =INDEX('list-countries'!$B$2:$B$203,MATCH(E186,'list-countries'!$C$2:$C$203,0)) -> Argentina | E186: =LEFT(B186,3) -> ARG | F186: =RIGHT(B186,LEN(B186)-3) -> CUR | G186: 40896 | H186: Daily
B187: ARMBOT | C187: Balance of Trade | D187: Armenia | E187: ARM | F187: BOT | G187: 37652 | H187: Monthly
B188: ARMCA | C188: Current Account | D188: Armenia | E188: ARM | F188: CA | G188: 34015 | H188: Quarterly
B189: ARMCAGDP | C189: Current Account to GDP | D189: Armenia | E189: ARM | F189: CAGDP | G189: 35064 | H189: Yearly
B190: ARMCCPI | C190: Core Consumer Prices | D190: Armenia | E190: ARM | F190: CCPI | G190: 38732 | H190: Monthly
B191: ARMCF | C191: Capital Flows | D191: Armenia | E191: ARM | F191: CF | G191: 34150 | H191: Yearly
B192: ARMCINF | C192: Core Inflation Rate | D192: Armenia | E192: ARM | F192: CINF | G192: 38732 | H192: Monthly
B193: ARMCNCN | C193: Consumer Confidence | D193: Armenia | E193: ARM | F193: CNCN | G193: 38579 | H193: Quarterly
B194: ARMCPI | C194: Consumer Price Index (CPI) | D194: Armenia | E194: ARM | F194: CPI | G194: 35079 | H194: Monthly
B195: ARMCPIC | C195: Inflation Rate | D195: Armenia | E195: ARM | F195: CPIC | G195: 34318 | H195: Monthly
B196: ARMCTR | C196: Corporate Tax Rate | D196: Armenia | E196: ARM | F196: CTR | G196: 38718 | H196: Yearly
B197: ARMEDBT | C197: External Debt | D197: Armenia | E197: ARM | F197: EDBT | G197: 35430 | H197: Yearly
B198: ARMEXVOL | C198: Exports | D198: Armenia | E198: ARM | F198: EXVOL | G198: 37652 | H198: Monthly
... B224: ARMWAGE | C224: Average Wages | D224: Armenia | E224: ARM | F224: WAGE | G224: 36616 | H224: Quarterly
B225: ARMCUR | C225: =INDEX('list-indicators'!$A$2:$A$293, MATCH(F225,'list-indicators'!$B$2:$B$293,0)) -> Currency Exchange Rate | D225: =INDEX('list-countries'!$B$2:$B$203,MATCH(E225,'list-countries'!$C$2:$C$203,0)) -> Armenia | E225: =LEFT(B225,3) -> ARM | F225: =RIGHT(B225,LEN(B225)-3) -> CUR | G225: 36191 | H225: Daily
B226: ABWBOT | C226: Balance Of Trade | D226: Aruba | E226: ABW | F226: BOT | G226: 36616 | H226: Quarterly
B227: ABWCPIC | C227: Inflation Rate | D227: Aruba | E227: ABW | F227: CPIC | G227: 36540 | H227: Monthly
B228: ABWCTR | C228: Corporate Tax Rate | D228: Aruba | E228: ABW | F228: CTR | G228: 38718 | H228: Yearly
B229: ABWEXVOL | C229: Exports | D229: Aruba | E229: ABW | F229: EXVOL | G229: 36616 | H229: Quarterly
B230: ABWGBGT | C230: Government Budget | D230: Aruba | E230: ABW | F230: GBGT | G230: 35064 | H230: Yearly
B231: ABWGOLD | C231: Gold Reserves | D231: Aruba | E231: ABW | F231: GOLD | G231: 36616 | H231: Quarterly
B232: ABWIMVOL | C232: Imports | D232: Aruba | E232: ABW | F232: IMVOL | G232: 36616 | H232: Quarterly
B233: ABWPITR | C233: Personal Income Tax Rate | D233: Aruba | E233: ABW | F233: PITR | G233: 37987 | H233: Yearly
B234: ABWSTR | C234: Sales Tax Rate | D234: Aruba | E234: ABW | F234: STR | G234: 39083 | H234: Yearly
B235: AUSBCONF | C235: Business Confidence | D235: Australia | E235: AUS | F235: BCONF | G235: 35520 | H235: Monthly
B236: AUSBOT | C236: Balance of Trade | D236: Australia | E236: AUS | F236: BOT | G236: 26129 | H236: Monthly
B237: AUSBP | C237: Building Permits | D237: Australia | E237: AUS | F237: BP | G237: 30543 | H237: Monthly
... B317: AUSWAGE | C317: Average Weekly Wages | D317: Australia | E317: AUS | F317: WAGE | G317: 25476 | H317: Quarterly
B318: AUSCOP | C318: =INDEX('list-indicators'!$A$2:$A$293, MATCH(F318,'list-indicators'!$B$2:$B$293,0)) -> Construction Output | D318: =INDEX('list-countries'!$B$2:$B$203,MATCH(E318,'list-countries'!$C$2:$C$203,0)) -> Australia | E318: =LEFT(B318,3) -> AUS | F318: =RIGHT(B318,LEN(B318)-3) -> COP | G318: 31731 | H318: Quarterly
B319: AUSCUR | C319: =INDEX('list-indicators'!$A$2:$A$293, MATCH(F319,'list-indicators'!$B$2:$B$293,0)) -> Currency Exchange Rate | D319: =INDEX('list-countries'!$B$2:$B$203,MATCH(E319,'list-countries'!$C$2:$C$203,0)) -> Australia | E319: =LEFT(B319,3) -> AUS | F319: =RIGHT(B319,LEN(B319)-3) -> CUR | G319: 40808 | H319: Daily
...

Sheet by-country
D1: Quandl Code | E1: Indicator Name | F1: Country Name | G1: Country Code | H1: Indicator Code | I1: Start Date | J1: Frequency
B2: Afghanistan | C2: AFG | D2: AFGBOT | E2: Balance of Trade | F2: Afghanistan | G2: AFG | H2: BOT | I2: 37711 | J2: Yearly
D3: AFGCA | E3: Current Account | F3: Afghanistan | G3: AFG | H3: CA | I3: 37711 | J3: Yearly
D4: AFGCAGDP | E4: Current Account to GDP | F4: Afghanistan | G4: AFG | H4: CAGDP | I4: 37711 | J4: Yearly
D5: AFGCPIC | E5: Inflation Rate | F5: Afghanistan | G5: AFG | H5: CPIC | I5: 38442 | J5: Monthly
D6: AFGCTR | E6: Corporate Tax Rate | F6: Afghanistan | G6: AFG | H6: CTR | I6: 38718 | J6: Yearly
D7: AFGEXVOL | E7: Exports | F7: Afghanistan | G7: AFG | H7: EXVOL | I7: 36616 | J7: Yearly
D8: AFGG | E8: GDP | F8: Afghanistan | G8: AFG | H8: G | I8: 22281 | J8: Yearly
D9: AFGGAGR | E9: GDP Annual Growth Rate | F9: Afghanistan | G9: AFG | H9: GAGR | I9: 37711 | J9: Yearly
D10: AFGGBGT | E10: Government Budget | F10: Afghanistan | G10: AFG | H10: GBGT | I10: 38807 | J10: Yearly
D11: AFGGDG | E11: Government Debt to GDP | F11: Afghanistan | G11: AFG | H11: GDG | I11: 38807 | J11: Yearly
D12: AFGGOLD | E12: Gold Reserves | F12: Afghanistan | G12: AFG | H12: GOLD | I12: 39721 | J12: Quarterly
D13: AFGGPC | E13: GDP per capita | F13: Afghanistan | G13: AFG | H13: GPC | I13: 22281 | J13: Yearly
D14: AFGGPCP | E14: GDP per capita PPP | F14: Afghanistan | G14: AFG | H14: GPCP | I14: 37621 | J14: Yearly
... D20: AFGUNR | E20: Unemployment Rate | F20: Afghanistan | G20: AFG | H20: UNR | I20: 33603 | J20: Yearly
B22: Albania | C22: ALB | D22: ALBBCONF | E22: Business Confidence | F22: Albania | G22: ALB | H22: BCONF | I22: 37437 | J22: Quarterly
D23: ALBBOT | E23: Balance of Trade | F23: Albania | G23: ALB | H23: BOT | I23: 33984 | J23: Monthly
D24: ALBCA | E24: Current Account | F24: Albania | G24: ALB | H24: CA | I24: 33984 | J24: Monthly
D25: ALBCAGDP | E25: Current Account to GDP | F25: Albania | G25: ALB | H25: CAGDP | I25: 29586 | J25: Yearly
D26: ALBCF | E26: Capital Flows | F26: Albania | G26: ALB | H26: CF | I26: 38001 | J26: Monthly
D27: ALBCNCN | E27: Consumer Confidence | F27: Albania | G27: ALB | H27: CNCN | I27: 37802 | J27: Quarterly
D28: ALBCPI | E28: Consumer Price Index (CPI) | F28: Albania | G28: ALB | H28: CPI | I28: 38732 | J28: Monthly
D29: ALBCPIC | E29: Inflation Rate | F29: Albania | G29: ALB | H29: CPIC | I29: 34730 | J29: Monthly
D30: ALBCPICM | E30: Inflation Rate MoM | F30: Albania | G30: ALB | H30: CPICM | I30: 38763 | J30: Monthly
D31: ALBCSP | E31: Consumer Spending | F31: Albania | G31: ALB | H31: CSP | I31: 35246 | J31: Yearly
D32: ALBCTR | E32: Corporate Tax Rate | F32: Albania | G32: ALB | H32: CTR | I32: 38718 | J32: Yearly
D33: ALBDINV | E33: Changes in Inventories | F33: Albania | G33: ALB | H33: DINV | I33: 35246 | J33: Yearly
D34: ALBEMP | E34: Employed Persons | F34: Albania | G34: ALB | H34: EMP | I34: 34288 | J34: Quarterly
... D64: ALBWAGE | E64: Average Monthly Wages | F64: Albania | G64: ALB | H64: WAGE | I64: 34288 | J64: Quarterly
B66: Algeria | C66: DZA | D66: DZABOT | E66: Balance of Trade | F66: Algeria | G66: DZA | H66: BOT | I66: 33785 | J66: Monthly
D67: DZACA | E67: Current Account | F67: Algeria | G67: DZA | H67: CA | I67: 33969 | J67: Quarterly
D68: DZACAGDP | E68: Current Account to GDP | F68: Algeria | G68: DZA | H68: CAGDP | I68: 29586 | J68: Yearly
D69: DZACPIC | E69: Inflation Rate | F69: Algeria | G69: DZA | H69: CPIC | I69: 37256 | J69: Monthly
D70: DZACSP | E70: Consumer Spending | F70: Algeria | G70: DZA | H70: CSP | I70: 34880 | J70: Yearly
D71: DZACTR | E71: Corporate Tax Rate | F71: Algeria | G71: DZA | H71: CTR | I71: 40909 | J71: Yearly
D72: DZADINV | E72: Changes in Inventories | F72: Algeria | G72: DZA | H72: DINV | I72: 34880 | J72: Yearly
D73: DZAEXVOL | E73: Exports | F73: Algeria | G73: DZA | H73: EXVOL | I73: 33785 | J73: Monthly
D74: DZAFINF | E74: Food Inflation | F74: Algeria | G74: DZA | H74: FINF | I74: 40466 | J74: Monthly
D75: DZAG | E75: GDP | F75: Algeria | G75: DZA | H75: G | I75: 22281 | J75: Yearly
D76: DZAGAGR | E76: GDP Annual Growth Rate | F76: Algeria | G76: DZA | H76: GAGR | I76: 37256 | J76: Yearly
D77: DZAGBGT | E77: Government Budget | F77: Algeria | G77: DZA | H77: GBGT | I77: 33238 | J77: Yearly
D78: DZAGCP | E78: GDP Constant Prices | F78: Algeria | G78: DZA | H78: GCP | I78: 25749 | J78: Yearly
... D95: DZAUNR | E95: Unemployment Rate | F95: Algeria | G95: DZA | H95: UNR | I95: 36433 | J95: Yearly
B97: Andorra | C97: AND | D97: ANDSTR | E97: Sales Tax Rate | VAT | F97: Andorra | G97: AND | H97: STR | I97: 41275 | J97: Yearly
B99: Angola | C99: AGO | D99: AGOBCONF | E99: Business Confidence | F99: Angola | G99: AGO | H99: BCONF | I99: 39721 | J99: Quarterly
D100: AGOBOT | E100: Balance of Trade | F100: Angola | G100: AGO | H100: BOT | I100: 37621 | J100: Quarterly
D101: AGOCA | E101: Current Account | F101: Angola | G101: AGO | H101: CA | I101: 36891 | J101: Yearly
D102: AGOCAGDP | E102: Current Account to GDP | F102: Angola | G102: AGO | H102: CAGDP | I102: 29586 | J102: Yearly
D103: AGOCPI | E103: Consumer Price Index (CPI) | F103: Angola | G103: AGO | H103: CPI | I103: 33984 | J103: Monthly
D104: AGOCPIC | E104: Inflation Rate | F104: Angola | G104: AGO | H104: CPIC | I104: 36922 | J104: Monthly
D105: AGOCPICM | E105: Inflation Rate MoM | F105: Angola | G105: AGO | H105: CPICM | I105: 40557 | J105: Monthly
D106: AGOCTR | E106: Corporate Tax Rate | F106: Angola | G106: AGO | H106: CTR | I106: 38718 | J106: Yearly
D107: AGOEXVOL | E107: Exports | F107: Angola | G107: AGO | H107: EXVOL | I107: 37621 | J107: Quarterly
D108: AGOFINF | E108: Food Inflation | F108: Angola | G108: AGO | H108: FINF | I108: 37636 | J108: Monthly
D109: AGOG | E109: GDP | F109: Angola | G109: AGO | H109: G | I109: 31412 | J109: Yearly
D110: AGOGAGR | E110: GDP Annual Growth Rate | F110: Angola | G110: AGO | H110: GAGR | I110: 36891 | J110: Yearly
D111: AGOGBGT | E111: Government Budget | F111: Angola | G111: AGO | H111: GBGT | I111: 37986 | J111: Yearly
... D123: AGOUNR | E123: Unemployment Rate | F123: Angola | G123: AGO | H123: UNR | I123: 38717 | J123: Yearly
B125: Antigua and Barbuda | C125: ATG | D125: ATGG | E125: GDP | F125: Antigua and Barbuda | G125: ATG | H125: G | I125: 28490 | J125: Yearly
D126: ATGGPCP | E126: GDP Per Capita PPP | F126: Antigua and Barbuda | G126: ATG | H126: GPCP | I126: 29586 | J126: Yearly
D127: ATGSTR | E127: Sales Tax Rate | VAT | F127: Antigua and Barbuda | G127: ATG | H127: STR | I127: 41640 | J127: Yearly
B129: Argentina | C129: ARG | D129: ARGBOT | E129: Balance of Trade | F129: Argentina | G129: ARG | H129: BOT | I129: 20835 | J129: Monthly
D130: ARGCA | E130: Current Account | F130: Argentina | G130: ARG | H130: CA | I130: 27805 | J130: Quarterly
D131: ARGCAGDP | E131: Current Account to GDP | F131: Argentina | G131: ARG | H131: CAGDP | I131: 29586 | J131: Yearly
D132: ARGCARS | E132: Domestic Car Sales | F132: Argentina | G132: ARG | H132: CARS | I132: 35079 | J132: Monthly
D133: ARGCF | E133: Capital Flows | F133: Argentina | G133: ARG | H133: CF | I133: 32919 | J133: Quarterly
D134: ARGCNCN | E134: Consumer Confidence | F134: Argentina | G134: ARG | H134: CNCN | I134: 36965 | J134: Monthly
D135: ARGCPI | E135: Consumer Price Index (CPI) | F135: Argentina | G135: ARG | H135: CPI | I135: 18278 | J135: Monthly
D136: ARGCPIC | E136: Inflation Rate | F136: Argentina | G136: ARG | H136: CPIC | I136: 16102 | J136: Monthly
D137: ARGCPICM | E137: Inflation Rate MoM | F137: Argentina | G137: ARG | H137: CPICM | I137: 41654 | J137: Monthly
D138: ARGCSP | E138: Consumer Spending | F138: Argentina | G138: ARG | H138: CSP | I138: 38032 | J138: Quarterly
D139: ARGCTR | E139: Corporate Tax Rate | F139: Argentina | G139: ARG | H139: CTR | I139: 38718 | J139: Yearly
D140: ARGCU | E140: Capacity Utilization | F140: Argentina | G140: ARG | H140: CU | I140: 37271 | J140: Monthly
D141: ARGDINV | E141: Changes in Inventories | F141: Argentina | G141: ARG | H141: DINV | I141: 34015 | J141: Quarterly
... D187: ARGWAGE | E187: Wage Index | F187: Argentina | G187: ARG | H187: WAGE | I187: 37179 | J187: Monthly
B189: Armenia | C189: ARM | D189: ARMBOT | E189: Balance of Trade | F189: Armenia | G189: ARM | H189: BOT | I189: 37652 | J189: Monthly
D190: ARMCA | E190: Current Account | F190: Armenia | G190: ARM | H190: CA | I190: 34015 | J190: Quarterly
D191: ARMCAGDP | E191: Current Account to GDP | F191: Armenia | G191: ARM | H191: CAGDP | I191: 35064 | J191: Yearly
D192: ARMCCPI | E192: Core Consumer Prices | F192: Armenia | G192: ARM | H192: CCPI | I192: 38732 | J192: Monthly
D193: ARMCF | E193: Capital Flows | F193: Armenia | G193: ARM | H193: CF | I193: 34150 | J193: Yearly
D194: ARMCINF | E194: Core Inflation Rate | F194: Armenia | G194: ARM | H194: CINF | I194: 38732 | J194: Monthly
D195: ARMCNCN | E195: Consumer Confidence | F195: Armenia | G195: ARM | H195: CNCN | I195: 38579 | J195: Quarterly
D196: ARMCPI | E196: Consumer Price Index (CPI) | F196: Armenia | G196: ARM | H196: CPI | I196: 35079 | J196: Monthly
D197: ARMCPIC | E197: Inflation Rate | F197: Armenia | G197: ARM | H197: CPIC | I197: 34318 | J197: Monthly
D198: ARMCTR | E198: Corporate Tax Rate | F198: Armenia | G198: ARM | H198: CTR | I198: 38718 | J198: Yearly
D199: ARMEDBT | E199: External Debt | F199: Armenia | G199: ARM | H199: EDBT | I199: 35430 | J199: Yearly
D200: ARMEXVOL | E200: Exports | F200: Armenia | G200: ARM | H200: EXVOL | I200: 37652 | J200: Monthly
D201: ARMG | E201: GDP | F201: Armenia | G201: ARM | H201: G | I201: 33238 | J201: Yearly
... D226: ARMWAGE | E226: Average Wages | F226: Armenia | G226: ARM | H226: WAGE | I226: 36616 | J226: Quarterly
B228: Aruba | C228: ABW | D228: ABWBOT | E228: Balance Of Trade | F228: Aruba | G228: ABW | H228: BOT | I228: 36616 | J228: Quarterly
D229: ABWCPIC | E229: Inflation Rate | F229: Aruba | G229: ABW | H229: CPIC | I229: 36540 | J229: Monthly
D230: ABWCTR | E230: Corporate Tax Rate | F230: Aruba | G230: ABW | H230: CTR | I230: 38718 | J230: Yearly
D231: ABWEXVOL | E231: Exports | F231: Aruba | G231: ABW | H231: EXVOL | I231: 36616 | J231: Quarterly
D232: ABWGBGT | E232: Government Budget | F232: Aruba | G232: ABW | H232: GBGT | I232: 35064 | J232: Yearly
D233: ABWGOLD | E233: Gold Reserves | F233: Aruba | G233: ABW | H233: GOLD | I233: 36616 | J233: Quarterly
D234: ABWIMVOL | E234: Imports | F234: Aruba | G234: ABW | H234: IMVOL | I234: 36616 | J234: Quarterly
D235: ABWPITR | E235: Personal Income Tax Rate | F235: Aruba | G235: ABW | H235: PITR | I235: 37987 | J235: Yearly
D236: ABWSTR | E236: Sales Tax Rate | F236: Aruba | G236: ABW | H236: STR | I236: 39083 | J236: Yearly
B238: Australia | C238: AUS | D238: AUSBCONF | E238: Business Confidence | F238: Australia | G238: AUS | H238: BCONF | I238: 35520 | J238: Monthly
D239: AUSBOT | E239: Balance of Trade | F239: Australia | G239: AUS | H239: BOT | I239: 26129 | J239: Monthly
...

Sheet by-indicator
D1: Quandl Code | E1: Indicator Name | F1: Country Name | G1: Country Code | H1: Indicator Code
B2: Adp Employment Change | C2: ADP | D2: USAADP | E2: Adp Employment Change | F2: United States | G2: USA | H2: ADP
B4: New Yuan Loans | C4: BBS | D4: CHNBBS | E4: New Yuan Loans | F4: China | G4: CHN | H4: BBS
B6: Business Confidence | C6: BCONF | D6: ALBBCONF | E6: Business Confidence | F6: Albania | G6: ALB | H6: BCONF
D7: AGOBCONF | E7: Business Confidence | F7: Angola | G7: AGO | H7: BCONF
D8: AUSBCONF | E8: Business Confidence | F8: Australia | G8: AUS | H8: BCONF
D9: AUTBCONF | E9: Business Confidence | F9: Austria | G9: AUT | H9: BCONF
D10: BELBCONF | E10: Business Confidence | F10: Belgium | G10: BEL | H10: BCONF
D11: BRABCONF | E11: Business Confidence | F11: Brazil | G11: BRA | H11: BCONF
D12: BGRBCONF | E12: Business Confidence | F12: Bulgaria | G12: BGR | H12: BCONF
D13: CANBCONF | E13: Business Confidence | F13: Canada | G13: CAN | H13: BCONF
D14: CPVBCONF | E14: Business Confidence | F14: Cape Verde | G14: CPV | H14: BCONF
D15: CHLBCONF | E15: Business Confidence | F15: Chile | G15: CHL | H15: BCONF
D16: CHNBCONF | E16: Business Confidence | F16: China | G16: CHN | H16: BCONF
D17: COLBCONF | E17: Business Confidence | F17: Colombia | G17: COL | H17: BCONF
D18: CYPBCONF | E18: Business Confidence | F18: Cyprus | G18: CYP | H18: BCONF
... D68: USABCONF | E68: Purchasing Managers Index (PMI) | F68: United States | G68: USA | H68: BCONF
B70: Business Inventories | C70: BI | D70: USABI | E70: Business Inventories | F70: United States | G70: USA | H70: BI
B72: Prime Lending Rate | C72: BLR | D72: AUTBLR | E72: Prime Lending Rate | F72: Austria | G72: AUT | H72: BLR
D73: BRABLR | E73: Bank Lending Rate | F73: Brazil | G73: BRA | H73: BLR
D74: CANBLR | E74: Prime Lending Rate | F74: Canada | G74: CAN | H74: BLR
D75: CHNBLR | E75: Prime Lending Rate | F75: China | G75: CHN | H75: BLR
D76: HRVBLR | E76: Bank Lending Rate | F76: Croatia | G76: HRV | H76: BLR
D77: FINBLR | E77: Bank Lending Rate | F77: Finland | G77: FIN | H77: BLR
D78: DEUBLR | E78: Bank Lending Rate | F78: Germany | G78: DEU | H78: BLR
D79: HKGBLR | E79: Prime Lending Rate | F79: Hong Kong | G79: HKG | H79: BLR
D80: HUNBLR | E80: Interest Rate on Collateralized Loans | F80: Hungary | G80: HUN | H80: BLR
D81: INDBLR | E81: Prime Lending Rate | F81: India | G81: IND | H81: BLR
D82: IRLBLR | E82: Clearing Banks Prime Rate | F82: Ireland | G82: IRL | H82: BLR
D83: ISRBLR | E83: Bank Prime Rate | F83: Israel | G83: ISR | H83: BLR
D84: JPNBLR | E84: Long Term Prime Rate | F84: Japan | G84: JPN | H84: BLR
... D104: USABLR | E104: Average Monthly Prime Lending Rate | F104: United States | G104: USA | H104: BLR
B106: Balance of Trade | C106: BOT | D106: AFGBOT | E106: Balance of Trade | F106: Afghanistan | G106: AFG | H106: BOT
D107: ALBBOT | E107: Balance of Trade | F107: Albania | G107: ALB | H107: BOT
D108: DZABOT | E108: Balance of Trade | F108: Algeria | G108: DZA | H108: BOT
D109: AGOBOT | E109: Balance of Trade | F109: Angola | G109: AGO | H109: BOT
D110: ARGBOT | E110: Balance of Trade | F110: Argentina | G110: ARG | H110: BOT
D111: ARMBOT | E111: Balance of Trade | F111: Armenia | G111: ARM | H111: BOT
D112: ABWBOT | E112: Balance Of Trade | F112: Aruba | G112: ABW | H112: BOT
D113: AUSBOT | E113: Balance of Trade | F113: Australia | G113: AUS | H113: BOT
D114: AUTBOT | E114: Balance of Trade | F114: Austria | G114: AUT | H114: BOT
D115: AZEBOT | E115: Balance of Trade | F115: Azerbaijan | G115: AZE | H115: BOT
D116: BHSBOT | E116: Balance of Trade | F116: Bahamas | G116: BHS | H116: BOT
D117: BHRBOT | E117: Balance of Trade | F117: Bahrain | G117: BHR | H117: BOT
D118: BGDBOT | E118: Balance of Trade | F118: Bangladesh | G118: BGD | H118: BOT
... D288: ZWEBOT | E288: Balance of Trade | F288: Zimbabwe | G288: ZWE | H288: BOT
B290: Building Permits | C290: BP | D290: AUSBP | E290: Building Permits | F290: Australia | G290: AUS | H290: BP
D291: BELBP | E291: Residential Building Permits | F291: Belgium | G291: BEL | H291: BP
D292: CANBP | E292: Building Permits | F292: Canada | G292: CAN | H292: BP
D293: FJIBP | E293: Building Permits | F293: Fiji | G293: FJI | H293: BP
D294: NZLBP | E294: Building Permits | F294: New Zealand | G294: NZL | H294: BP
D295: USABP | E295: Building Permits | F295: United States | G295: USA | H295: BP
B297: Bankruptcies | C297: BR | D297: AUSBR | E297: Bankruptcies | F297: Australia | G297: AUS | H297: BR
D298: BELBR | E298: Bankruptcies | F298: Belgium | G298: BEL | H298: BR
D299: CANBR | E299: Bankruptcies | F299: Canada | G299: CAN | H299: BR
D300: DNKBR | E300: Bankruptcies | F300: Denmark | G300: DNK | H300: BR
D301: FINBR | E301: Bankruptcies | F301: Finland | G301: FIN | H301: BR
D302: FRABR | E302: Bankruptcies | F302: France | G302: FRA | H302: BR
D303: DEUBR | E303: Bankruptcies | F303: Germany | G303: DEU | H303: BR
D304: HKGBR | E304: Bankruptcies | F304: Hong Kong | G304: HKG | H304: BR
D305: JPNBR | E305: Bankruptcies | F305: Japan | G305: JPN | H305: BR
D306: LUXBR | E306: Bankruptcies | F306: Luxembourg | G306: LUX | H306: BR
D307: MYSBR | E307: Bankruptcies | F307: Malaysia | G307: MYS | H307: BR
D308: NLDBR | E308: Bankruptcies | F308: Netherlands | G308: NLD | H308: BR
D309: NORBR | E309: Bankruptcies | F309: Norway | G309: NOR | H309: BR
... D319: USABR | E319: Bankruptcies | F319: United States | G319: USA | H319: BR
B321: Current Account | C321: CA | D321: AFGCA | E321: Current Account | F321: Afghanistan | G321: AFG | H321: CA
D322: ALBCA | E322: Current Account | F322: Albania | G322: ALB | H322: CA
D323: DZACA | E323: Current Account | F323: Algeria | G323: DZA | H323: CA
D324: AGOCA | E324: Current Account | F324: Angola | G324: AGO | H324: CA
D325: ARGCA | E325: Current Account | F325: Argentina | G325: ARG | H325: CA
D326: ARMCA | E326: Current Account | F326: Armenia | G326: ARM | H326: CA
D327: AUSCA | E327: Current Account | F327: Australia | G327: AUS | H327: CA
D328: AUTCA | E328: Current Account | F328: Austria | G328: AUT | H328: CA
D329: AZECA | E329: Current Account | F329: Azerbaijan | G329: AZE | H329: CA
D330: BHSCA | E330: Current Account | F330: Bahamas | G330: BHS | H330: CA
D331: BHRCA | E331: Current Account | F331: Bahrain | G331: BHR | H331: CA
D332: BGDCA | E332: Current Account | F332: Bangladesh | G332: BGD | H332: CA
D333: BLRCA | E333: Current Account | F333: Belarus | G333: BLR | H333: CA
... D496: ZWECA | E496: Current Account | F496: Zimbabwe | G496: ZWE | H496: CA
B498: Current Account to GDP | C498: CAGDP | D498: AFGCAGDP | E498: Current Account to GDP | F498: Afghanistan | G498: AFG | H498: CAGDP
D499: ALBCAGDP | E499: Current Account to GDP | F499: Albania | G499: ALB | H499: CAGDP
D500: DZACAGDP | E500: Current Account to GDP | F500: Algeria | G500: DZA | H500: CAGDP
D501: AGOCAGDP | E501: Current Account to GDP | F501: Angola | G501: AGO | H501: CAGDP
D502: ARGCAGDP | E502: Current Account to GDP | F502: Argentina | G502: ARG | H502: CAGDP
D503: ARMCAGDP | E503: Current Account to GDP | F503: Armenia | G503: ARM | H503: CAGDP
D504: AUSCAGDP | E504: Current Account to GDP | F504: Australia | G504: AUS | H504: CAGDP
D505: AUTCAGDP | E505: Current Account to GDP | F505: Austria | G505: AUT | H505: CAGDP
D506: AZECAGDP | E506: Current Account to GDP | F506: Azerbaijan | G506: AZE | H506: CAGDP
D507: BHSCAGDP | E507: Current Account to GDP | F507: Bahamas | G507: BHS | H507: CAGDP
D508: BHRCAGDP | E508: Current Account to GDP | F508: Bahrain | G508: BHR | H508: CAGDP
D509: BGDCAGDP | E509: Current Account to GDP | F509: Bangladesh | G509: BGD | H509: CAGDP
D510: BLRCAGDP | E510: Current Account to GDP | F510: Belarus | G510: BLR | H510: CAGDP
... D672: ZWECAGDP | E672: Current Account to GDP | F672: Zimbabwe | G672: ZWE | H672: CAGDP
B674: Domestic Car Sales | C674: CARS | D674: ARGCARS | E674: Domestic Car Sales | F674: Argentina | G674: ARG | H674: CARS
D675: AUSCARS | E675: New Car Sales | F675: Australia | G675: AUS | H675: CARS
D676: AUTCARS | E676: Car Registrations | F676: Austria | G676: AUT | H676: CARS
D677: BHRCARS | E677: Car Registrations | F677: Bahrain | G677: BHR | H677: CARS
D678: BELCARS | E678: Car Registrations | F678: Belgium | G678: BEL | H678: CARS
D679: BRACARS | E679: Car Registrations | F679: Brazil | G679: BRA | H679: CARS
...

Sheet matrix
C2: Country | D2: Afghanistan | E2: Albania | F2: Algeria | G2: Andorra | H2: Angola | I2: Antigua and Barbuda | J2: Argentina | K2: Armenia | L2: Aruba | M2: Australia | N2: Austria | O2: Azerbaijan | P2: Bahamas | Q2: Bahrain | R2: Bangladesh | S2: Barbados | T2: Belarus | U2: Belgium | V2: Belize | W2: Benin | X2: Bermuda | Y2: Bhutan | Z2: Bolivia | AA2: Bosnia and Herzegovina | AB2: Botswana | AC2: Brazil | AD2: Brunei | AE2: Bulgaria | AF2: Burkina Faso | AG2: Burundi | AH2: Cambodia | AI2: Cameroon | AJ2: Canada | AK2: Cape Verde | AL2: Cayman Islands | AM2: Central African Republic | AN2: Chad | AO2: Chile | AP2: China | AQ2: Colombia | AR2: Comoros | AS2: Congo | AT2: Costa Rica | AU2: Croatia | AV2: Cuba | AW2: Cyprus | AX2: Czech Republic | AY2: Denmark | AZ2: Djibouti | BA2: Dominica | BB2: Dominican Republic | BC2: East Timor | BD2: Ecuador | BE2: Egypt | BF2: El Salvador | BG2: Equatorial Guinea | BH2: Eritrea | BI2: Estonia | BJ2: Ethiopia | BK2: Euro area | BL2: Fiji | BM2: Finland | BN2: France | BO2: Gabon | BP2: Gambia | BQ2: Georgia | BR2: Germany | BS2: Ghana | BT2: Greece | BU2: Greenland | BV2: Grenada | BW2: Guam | BX2: Guatemala | BY2: Guinea | BZ2: Guinea Bissau | CA2: Guyana | CB2: Haiti | CC2: Honduras | CD2: Hong Kong | CE2: Hungary | CF2: Iceland | CG2: India | CH2: Indonesia | CI2: Iran | CJ2: Iraq | CK2: Ireland | CL2: Isle of Man | CM2: Israel | CN2: Italy | CO2: Ivory Coast | CP2: Jamaica | CQ2: Japan | CR2: Jordan | CS2: Kazakhstan | CT2: Kenya | CU2: Kiribati | CV2: Kuwait | CW2: Kyrgyzstan | CX2: Laos | CY2: Latvia | CZ2: Lebanon | DA2: Lesotho | DB2: Liberia | DC2: Libya | DD2: Liechtenstein | DE2: Lithuania | DF2: Luxembourg | DG2: Macao | DH2: Macedonia | DI2: Madagascar | DJ2: Malawi | DK2: Malaysia | DL2: Maldives | DM2: Mali | DN2: Malta | DO2: Mauritania | DP2: Mauritius | DQ2: Mexico | DR2: Micronesia | DS2: Moldova | DT2: Monaco | DU2: Mongolia | DV2: Montenegro | DW2: Morocco | DX2: Mozambique | DY2: Myanmar | DZ2: Namibia | EA2: Nepal | EB2: Netherlands | EC2: New Caledonia | ED2: New Zealand | EE2: Nicaragua | EF2: Niger | EG2: Nigeria | EH2: North Korea | EI2: Norway | EJ2: Oman | EK2: Pakistan | EL2: Palau | EM2: Palestine | EN2: Panama | EO2: Papua New Guinea | EP2: Paraguay | EQ2: Peru | ER2: Philippines | ES2: Poland | ET2: Portugal | EU2: Puerto Rico | EV2: Qatar | EW2: Republic of the Congo | EX2: Romania | EY2: Russia | EZ2: Rwanda | FA2: Samoa | FB2: Sao Tome and Principe | FC2: Saudi Arabia | FD2: Senegal | FE2: Serbia | FF2: Seychelles | FG2: Sierra Leone | FH2: Singapore | FI2: Slovakia | FJ2: Slovenia | FK2: Solomon Islands | FL2: Somalia | FM2: South Africa | FN2: South Korea | FO2: South Sudan | FP2: Spain | FQ2: Sri Lanka | FR2: St Kitts and Nevis | FS2: St Lucia | FT2: St Vincent and the Grenadines | FU2: Sudan | FV2: Suriname | FW2: Swaziland | FX2: Sweden | FY2: Switzerland | FZ2: Syria | GA2: Taiwan | GB2: Tajikistan | GC2: Tanzania | GD2: Thailand | GE2: Togo | GF2: Tonga | GG2: Trinidad and Tobago | GH2: Tunisia | GI2: Turkey | GJ2: Turkmenistan | GK2: Uganda | GL2: Ukraine | GM2: United Arab Emirates | GN2: United Kingdom | GO2: United States | GP2: Uruguay | GQ2: Uzbekistan | GR2: Vanuatu | GS2: Venezuela | GT2: Vietnam | GU2: Yemen | GV2: Zambia | GW2: Zimbabwe
B3: Indicator | D3: AFG | E3: ALB | F3: DZA | G3: AND | H3: AGO | I3: ATG | J3: ARG | K3: ARM | L3: ABW | M3: AUS | N3: AUT | O3: AZE | P3: BHS | Q3: BHR | R3: BGD | S3: BRB | T3: BLR | U3: BEL | V3: BLZ | W3: BEN | X3: BMU | Y3: BTN | Z3: BOL | AA3: BIH | AB3: BWA | AC3: BRA | AD3: BRN | AE3: BGR | AF3: BFA | AG3: BDI | AH3: KHM | AI3: CMR | AJ3: CAN | AK3: CPV | AL3: CYM | AM3: CAF | AN3: TCD | AO3: CHL | AP3: CHN | AQ3: COL | AR3: COM | AS3: COD | AT3: CRI | AU3: HRV | AV3: CUB | AW3: CYP | AX3: CZE | AY3: DNK | AZ3: DJI | BA3: DMA | BB3: DOM | BC3: TLS | BD3: ECU | BE3: EGY | BF3: SLV | BG3: GNQ | BH3: ERI | BI3: EST | BJ3: ETH | BK3: EUR | BL3: FJI | BM3: FIN | BN3: FRA | BO3: GAB | BP3: GMB | BQ3: GEO | BR3: DEU | BS3: GHA | BT3: GRC | BU3: GRL | BV3: GRD | BW3: GUM | BX3: GTM | BY3: GIN | BZ3: GNB | CA3: GUY | CB3: HTI | CC3: HND | CD3: HKG | CE3: HUN | CF3: ISL | CG3: IND | CH3: IDN | CI3: IRN | CJ3: IRQ | CK3: IRL | CL3: IMN | CM3: ISR | CN3: ITA | CO3: CIV | CP3: JAM | CQ3: JPN | CR3: JOR | CS3: KAZ | CT3: KEN | CU3: KIR | CV3: KWT | CW3: KGZ | CX3: LAO | CY3: LVA | CZ3: LBN | DA3: LSO | DB3: LBR | DC3: LBY | DD3: LIE | DE3: LTU | DF3: LUX | DG3: MAC | DH3: MKD | DI3: MDG | DJ3: MWI | DK3: MYS | DL3: MDV | DM3: MLI | DN3: MLT | DO3: MRT | DP3: MUS | DQ3: MEX | DR3: FSM | DS3: MDA | DT3: MCO | DU3: MNG | DV3: MNE | DW3: MAR | DX3: MOZ | DY3: MMR | DZ3: NAM | EA3: NPL | EB3: NLD | EC3: NCL | ED3: NZL | EE3: NIC | EF3: NER | EG3: NGA | EH3: PRK | EI3: NOR | EJ3: OMN | EK3: PAK | EL3: PLW | EM3: PSE | EN3: PAN | EO3: PNG | EP3: PRY | EQ3: PER | ER3: PHL | ES3: POL | ET3: PRT | EU3: PRI | EV3: QAT | EW3: COG | EX3: ROU | EY3: RUS | EZ3: RWA | FA3: WSM | FB3: STP | FC3: SAU | FD3: SEN | FE3: SRB | FF3: SYC | FG3: SLE | FH3: SGP | FI3: SVK | FJ3: SVN | FK3: SLB | FL3: SOM | FM3: ZAF | FN3: KOR | FO3: SSD | FP3: ESP | FQ3: LKA | FR3: KNA | FS3: LCA | FT3: VCT | FU3: SDN | FV3: SUR | FW3: SWZ | FX3: SWE | FY3: CHE | FZ3: SYR | GA3: TWN | GB3: TJK | GC3: TZA | GD3: THA | GE3: TGO | GF3: TON | GG3: TTO | GH3: TUN | GI3: TUR | GJ3: TKM | GK3: UGA | GL3: UKR | GM3: ARE | GN3: GBR | GO3: USA | GP3: URY | GQ3: UZB | GR3: VUT | GS3: VEN | GT3: VNM | GU3: YEM | GV3: ZMB | GW3: ZWE
B4: Adp Employment Change | C4: ADP | D4: =IF(ISNA(VLOOKUP(D$3&$C4,'all-data'!$B$2:$B$7345,1,FALSE)),"",D$3&$C4) | E4: =IF(ISNA(VLOOKUP(E$3&$C4,'all-data'!$B$2:$B$7345,1,FALSE)),"",E$3&$C4) | F4: =IF(ISNA(VLOOKUP(F$3&$C4,'all-data'!$B$2:$B$7345,1,FALSE)),"",F$3&$C4) | G4: =IF(ISNA(VLOOKUP(G$3&$C4,'all-data'!$B$2:$B$7345,1,FALSE)),"",G$3&$C4) | H4: =IF(ISNA(VLOOKUP(H$3&$C4,'all-data'!$B$2:$B$7345,1,FALSE)),"",H$3&$C4) | I4: =IF(ISNA(VLOOKUP(I$3&$C4,'all-data'!$B$2:$B$7345,1,FALSE)),"",I$3&$C4) | J4: =IF(ISNA(VLOOKUP(J$3&$C4,'all-data'!$B$2:$B$7345,1,FALSE)),"",J$3&$C4) | K4: =IF(ISNA(VLOOKUP(K$3&$C4,'all-data'!$B$2:$B$7345,1,FALSE)),"",K$3&$C4) | ... GW4: =IF(ISNA(VLOOKUP(GW$3&$C4,'all-data'!$B$2:$B$7345,1,FALSE)),"",GW$3&$C4)
B5: New Yuan Loans | C5: BBS | D5: =IF(ISNA(VLOOKUP(D$3&$C5,'all-data'!$B$2:$B$7345,1,FALSE)),"",D$3&$C5) | E5: =IF(ISNA(VLOOKUP(E$3&$C5,'all-data'!$B$2:$B$7345,1,FALSE)),"",E$3&$C5) | F5: =IF(ISNA(VLOOKUP(F$3&$C5,'all-data'!$B$2:$B$7345,1,FALSE)),"",F$3&$C5) | G5: =IF(ISNA(VLOOKUP(G$3&$C5,'all-data'!$B$2:$B$7345,1,FALSE)),"",G$3&$C5) | H5: =IF(ISNA(VLOOKUP(H$3&$C5,'all-data'!$B$2:$B$7345,1,FALSE)),"",H$3&$C5) | I5: =IF(ISNA(VLOOKUP(I$3&$C5,'all-data'!$B$2:$B$7345,1,FALSE)),"",I$3&$C5) | J5: =IF(ISNA(VLOOKUP(J$3&$C5,'all-data'!$B$2:$B$7345,1,FALSE)),"",J$3&$C5) | K5: =IF(ISNA(VLOOKUP(K$3&$C5,'all-data'!$B$2:$B$7345,1,FALSE)),"",K$3&$C5) | ... GW5: =IF(ISNA(VLOOKUP(GW$3&$C5,'all-data'!$B$2:$B$7345,1,FALSE)),"",GW$3&$C5)
B6: Business Confidence | C6: BCONF | D6: =IF(ISNA(VLOOKUP(D$3&$C6,'all-data'!$B$2:$B$7345,1,FALSE)),"",D$3&$C6) | E6: =IF(ISNA(VLOOKUP(E$3&$C6,'all-data'!$B$2:$B$7345,1,FALSE)),"",E$3&$C6) -> ALBBCONF | F6: =IF(ISNA(VLOOKUP(F$3&$C6,'all-data'!$B$2:$B$7345,1,FALSE)),"",F$3&$C6) | G6: =IF(ISNA(VLOOKUP(G$3&$C6,'all-data'!$B$2:$B$7345,1,FALSE)),"",G$3&$C6) | H6: =IF(ISNA(VLOOKUP(H$3&$C6,'all-data'!$B$2:$B$7345,1,FALSE)),"",H$3&$C6) -> AGOBCONF | I6: =IF(ISNA(VLOOKUP(I$3&$C6,'all-data'!$B$2:$B$7345,1,FALSE)),"",I$3&$C6) | J6: =IF(ISNA(VLOOKUP(J$3&$C6,'all-data'!$B$2:$B$7345,1,FALSE)),"",J$3&$C6) | K6: =IF(ISNA(VLOOKUP(K$3&$C6,'all-data'!$B$2:$B$7345,1,FALSE)),"",K$3&$C6) | ... GW6: =IF(ISNA(VLOOKUP(GW$3&$C6,'all-data'!$B$2:$B$7345,1,FALSE)),"",GW$3&$C6)
B7: Business Inventories | C7: BI | D7: =IF(ISNA(VLOOKUP(D$3&$C7,'all-data'!$B$2:$B$7345,1,FALSE)),"",D$3&$C7) | E7: =IF(ISNA(VLOOKUP(E$3&$C7,'all-data'!$B$2:$B$7345,1,FALSE)),"",E$3&$C7) | F7: =IF(ISNA(VLOOKUP(F$3&$C7,'all-data'!$B$2:$B$7345,1,FALSE)),"",F$3&$C7) | G7: =IF(ISNA(VLOOKUP(G$3&$C7,'all-data'!$B$2:$B$7345,1,FALSE)),"",G$3&$C7) | H7: =IF(ISNA(VLOOKUP(H$3&$C7,'all-data'!$B$2:$B$7345,1,FALSE)),"",H$3&$C7) | I7: =IF(ISNA(VLOOKUP(I$3&$C7,'all-data'!$B$2:$B$7345,1,FALSE)),"",I$3&$C7) | J7: =IF(ISNA(VLOOKUP(J$3&$C7,'all-data'!$B$2:$B$7345,1,FALSE)),"",J$3&$C7) | K7: =IF(ISNA(VLOOKUP(K$3&$C7,'all-data'!$B$2:$B$7345,1,FALSE)),"",K$3&$C7) | ... GW7: =IF(ISNA(VLOOKUP(GW$3&$C7,'all-data'!$B$2:$B$7345,1,FALSE)),"",GW$3&$C7)
B8: Prime Lending Rate | C8: BLR | D8: =IF(ISNA(VLOOKUP(D$3&$C8,'all-data'!$B$2:$B$7345,1,FALSE)),"",D$3&$C8) | E8: =IF(ISNA(VLOOKUP(E$3&$C8,'all-data'!$B$2:$B$7345,1,FALSE)),"",E$3&$C8) | F8: =IF(ISNA(VLOOKUP(F$3&$C8,'all-data'!$B$2:$B$7345,1,FALSE)),"",F$3&$C8) | G8: =IF(ISNA(VLOOKUP(G$3&$C8,'all-data'!$B$2:$B$7345,1,FALSE)),"",G$3&$C8) | H8: =IF(ISNA(VLOOKUP(H$3&$C8,'all-data'!$B$2:$B$7345,1,FALSE)),"",H$3&$C8) | I8: =IF(ISNA(VLOOKUP(I$3&$C8,'all-data'!$B$2:$B$7345,1,FALSE)),"",I$3&$C8) | J8: =IF(ISNA(VLOOKUP(J$3&$C8,'all-data'!$B$2:$B$7345,1,FALSE)),"",J$3&$C8) | K8: =IF(ISNA(VLOOKUP(K$3&$C8,'all-data'!$B$2:$B$7345,1,FALSE)),"",K$3&$C8) | ... GW8: =IF(ISNA(VLOOKUP(GW$3&$C8,'all-data'!$B$2:$B$7345,1,FALSE)),"",GW$3&$C8)
B9: Balance of Trade | C9: BOT | D9: =IF(ISNA(VLOOKUP(D$3&$C9,'all-data'!$B$2:$B$7345,1,FALSE)),"",D$3&$C9) -> AFGBOT | E9: =IF(ISNA(VLOOKUP(E$3&$C9,'all-data'!$B$2:$B$7345,1,FALSE)),"",E$3&$C9) -> ALBBOT | F9: =IF(ISNA(VLOOKUP(F$3&$C9,'all-data'!$B$2:$B$7345,1,FALSE)),"",F$3&$C9) -> DZABOT | G9: =IF(ISNA(VLOOKUP(G$3&$C9,'all-data'!$B$2:$B$7345,1,FALSE)),"",G$3&$C9) | H9: =IF(ISNA(VLOOKUP(H$3&$C9,'all-data'!$B$2:$B$7345,1,FALSE)),"",H$3&$C9) -> AGOBOT | I9: =IF(ISNA(VLOOKUP(I$3&$C9,'all-data'!$B$2:$B$7345,1,FALSE)),"",I$3&$C9) | J9: =IF(ISNA(VLOOKUP(J$3&$C9,'all-data'!$B$2:$B$7345,1,FALSE)),"",J$3&$C9) -> ARGBOT | K9: =IF(ISNA(VLOOKUP(K$3&$C9,'all-data'!$B$2:$B$7345,1,FALSE)),"",K$3&$C9) -> ARMBOT | ... GW9: =IF(ISNA(VLOOKUP(GW$3&$C9,'all-data'!$B$2:$B$7345,1,FALSE)),"",GW$3&$C9) -> ZWEBOT
B10: Building Permits | C10: BP | D10: =IF(ISNA(VLOOKUP(D$3&$C10,'all-data'!$B$2:$B$7345,1,FALSE)),"",D$3&$C10) | E10: =IF(ISNA(VLOOKUP(E$3&$C10,'all-data'!$B$2:$B$7345,1,FALSE)),"",E$3&$C10) | F10: =IF(ISNA(VLOOKUP(F$3&$C10,'all-data'!$B$2:$B$7345,1,FALSE)),"",F$3&$C10) | G10: =IF(ISNA(VLOOKUP(G$3&$C10,'all-data'!$B$2:$B$7345,1,FALSE)),"",G$3&$C10) | H10: =IF(ISNA(VLOOKUP(H$3&$C10,'all-data'!$B$2:$B$7345,1,FALSE)),"",H$3&$C10) | I10: =IF(ISNA(VLOOKUP(I$3&$C10,'all-data'!$B$2:$B$7345,1,FALSE)),"",I$3&$C10) | J10: =IF(ISNA(VLOOKUP(J$3&$C10,'all-data'!$B$2:$B$7345,1,FALSE)),"",J$3&$C10) | K10: =IF(ISNA(VLOOKUP(K$3&$C10,'all-data'!$B$2:$B$7345,1,FALSE)),"",K$3&$C10) | ... GW10: =IF(ISNA(VLOOKUP(GW$3&$C10,'all-data'!$B$2:$B$7345,1,FALSE)),"",GW$3&$C10)
B11: Bankruptcies | C11: BR | D11: =IF(ISNA(VLOOKUP(D$3&$C11,'all-data'!$B$2:$B$7345,1,FALSE)),"",D$3&$C11) | E11: =IF(ISNA(VLOOKUP(E$3&$C11,'all-data'!$B$2:$B$7345,1,FALSE)),"",E$3&$C11) | F11: =IF(ISNA(VLOOKUP(F$3&$C11,'all-data'!$B$2:$B$7345,1,FALSE)),"",F$3&$C11) | G11: =IF(ISNA(VLOOKUP(G$3&$C11,'all-data'!$B$2:$B$7345,1,FALSE)),"",G$3&$C11) | H11: =IF(ISNA(VLOOKUP(H$3&$C11,'all-data'!$B$2:$B$7345,1,FALSE)),"",H$3&$C11) | I11: =IF(ISNA(VLOOKUP(I$3&$C11,'all-data'!$B$2:$B$7345,1,FALSE)),"",I$3&$C11) | J11: =IF(ISNA(VLOOKUP(J$3&$C11,'all-data'!$B$2:$B$7345,1,FALSE)),"",J$3&$C11) | K11: =IF(ISNA(VLOOKUP(K$3&$C11,'all-data'!$B$2:$B$7345,1,FALSE)),"",K$3&$C11) | ... GW11: =IF(ISNA(VLOOKUP(GW$3&$C11,'all-data'!$B$2:$B$7345,1,FALSE)),"",GW$3&$C11)
B12: Current Account | C12: CA | D12: =IF(ISNA(VLOOKUP(D$3&$C12,'all-data'!$B$2:$B$7345,1,FALSE)),"",D$3&$C12) -> AFGCA | E12: =IF(ISNA(VLOOKUP(E$3&$C12,'all-data'!$B$2:$B$7345,1,FALSE)),"",E$3&$C12) -> ALBCA | F12: =IF(ISNA(VLOOKUP(F$3&$C12,'all-data'!$B$2:$B$7345,1,FALSE)),"",F$3&$C12) -> DZACA | G12: =IF(ISNA(VLOOKUP(G$3&$C12,'all-data'!$B$2:$B$7345,1,FALSE)),"",G$3&$C12) | H12: =IF(ISNA(VLOOKUP(H$3&$C12,'all-data'!$B$2:$B$7345,1,FALSE)),"",H$3&$C12) -> AGOCA | I12: =IF(ISNA(VLOOKUP(I$3&$C12,'all-data'!$B$2:$B$7345,1,FALSE)),"",I$3&$C12) | J12: =IF(ISNA(VLOOKUP(J$3&$C12,'all-data'!$B$2:$B$7345,1,FALSE)),"",J$3&$C12) -> ARGCA | K12: =IF(ISNA(VLOOKUP(K$3&$C12,'all-data'!$B$2:$B$7345,1,FALSE)),"",K$3&$C12) -> ARMCA | ... GW12: =IF(ISNA(VLOOKUP(GW$3&$C12,'all-data'!$B$2:$B$7345,1,FALSE)),"",GW$3&$C12) -> ZWECA
B13: Current Account to GDP | C13: CAGDP | D13: =IF(ISNA(VLOOKUP(D$3&$C13,'all-data'!$B$2:$B$7345,1,FALSE)),"",D$3&$C13) -> AFGCAGDP | E13: =IF(ISNA(VLOOKUP(E$3&$C13,'all-data'!$B$2:$B$7345,1,FALSE)),"",E$3&$C13) -> ALBCAGDP | F13: =IF(ISNA(VLOOKUP(F$3&$C13,'all-data'!$B$2:$B$7345,1,FALSE)),"",F$3&$C13) -> DZACAGDP | G13: =IF(ISNA(VLOOKUP(G$3&$C13,'all-data'!$B$2:$B$7345,1,FALSE)),"",G$3&$C13) | H13: =IF(ISNA(VLOOKUP(H$3&$C13,'all-data'!$B$2:$B$7345,1,FALSE)),"",H$3&$C13) -> AGOCAGDP | I13: =IF(ISNA(VLOOKUP(I$3&$C13,'all-data'!$B$2:$B$7345,1,FALSE)),"",I$3&$C13) | J13: =IF(ISNA(VLOOKUP(J$3&$C13,'all-data'!$B$2:$B$7345,1,FALSE)),"",J$3&$C13) -> ARGCAGDP | K13: =IF(ISNA(VLOOKUP(K$3&$C13,'all-data'!$B$2:$B$7345,1,FALSE)),"",K$3&$C13) -> ARMCAGDP | ... GW13: =IF(ISNA(VLOOKUP(GW$3&$C13,'all-data'!$B$2:$B$7345,1,FALSE)),"",GW$3&$C13) -> ZWECAGDP
B14: Domestic Car Sales | C14: CARS | D14: =IF(ISNA(VLOOKUP(D$3&$C14,'all-data'!$B$2:$B$7345,1,FALSE)),"",D$3&$C14) | E14: =IF(ISNA(VLOOKUP(E$3&$C14,'all-data'!$B$2:$B$7345,1,FALSE)),"",E$3&$C14) | F14: =IF(ISNA(VLOOKUP(F$3&$C14,'all-data'!$B$2:$B$7345,1,FALSE)),"",F$3&$C14) | G14: =IF(ISNA(VLOOKUP(G$3&$C14,'all-data'!$B$2:$B$7345,1,FALSE)),"",G$3&$C14) | H14: =IF(ISNA(VLOOKUP(H$3&$C14,'all-data'!$B$2:$B$7345,1,FALSE)),"",H$3&$C14) | I14: =IF(ISNA(VLOOKUP(I$3&$C14,'all-data'!$B$2:$B$7345,1,FALSE)),"",I$3&$C14) | J14: =IF(ISNA(VLOOKUP(J$3&$C14,'all-data'!$B$2:$B$7345,1,FALSE)),"",J$3&$C14) -> ARGCARS | K14: =IF(ISNA(VLOOKUP(K$3&$C14,'all-data'!$B$2:$B$7345,1,FALSE)),"",K$3&$C14) | ... GW14: =IF(ISNA(VLOOKUP(GW$3&$C14,'all-data'!$B$2:$B$7345,1,FALSE)),"",GW$3&$C14)
B15: Central Bank Balance Sheet | C15: CBBS | D15: =IF(ISNA(VLOOKUP(D$3&$C15,'all-data'!$B$2:$B$7345,1,FALSE)),"",D$3&$C15) | E15: =IF(ISNA(VLOOKUP(E$3&$C15,'all-data'!$B$2:$B$7345,1,FALSE)),"",E$3&$C15) | F15: =IF(ISNA(VLOOKUP(F$3&$C15,'all-data'!$B$2:$B$7345,1,FALSE)),"",F$3&$C15) | G15: =IF(ISNA(VLOOKUP(G$3&$C15,'all-data'!$B$2:$B$7345,1,FALSE)),"",G$3&$C15) | H15: =IF(ISNA(VLOOKUP(H$3&$C15,'all-data'!$B$2:$B$7345,1,FALSE)),"",H$3&$C15) | I15: =IF(ISNA(VLOOKUP(I$3&$C15,'all-data'!$B$2:$B$7345,1,FALSE)),"",I$3&$C15) | J15: =IF(ISNA(VLOOKUP(J$3&$C15,'all-data'!$B$2:$B$7345,1,FALSE)),"",J$3&$C15) | K15: =IF(ISNA(VLOOKUP(K$3&$C15,'all-data'!$B$2:$B$7345,1,FALSE)),"",K$3&$C15) | ... GW15: =IF(ISNA(VLOOKUP(GW$3&$C15,'all-data'!$B$2:$B$7345,1,FALSE)),"",GW$3&$C15)
... B145: Zew Economic Sentiment Index | C145: ZEW | D145: =IF(ISNA(VLOOKUP(D$3&$C145,'all-data'!$B$2:$B$7345,1,FALSE)),"",D$3&$C145) | E145: =IF(ISNA(VLOOKUP(E$3&$C145,'all-data'!$B$2:$B$7345,1,FALSE)),"",E$3&$C145) | F145: =IF(ISNA(VLOOKUP(F$3&$C145,'all-data'!$B$2:$B$7345,1,FALSE)),"",F$3&$C145) | G145: =IF(ISNA(VLOOKUP(G$3&$C145,'all-data'!$B$2:$B$7345,1,FALSE)),"",G$3&$C145) | H145: =IF(ISNA(VLOOKUP(H$3&$C145,'all-data'!$B$2:$B$7345,1,FALSE)),"",H$3&$C145) | I145: =IF(ISNA(VLOOKUP(I$3&$C145,'all-data'!$B$2:$B$7345,1,FALSE)),"",I$3&$C145) | J145: =IF(ISNA(VLOOKUP(J$3&$C145,'all-data'!$B$2:$B$7345,1,FALSE)),"",J$3&$C145) | K145: =IF(ISNA(VLOOKUP(K$3&$C145,'all-data'!$B$2:$B$7345,1,FALSE)),"",K$3&$C145) | ... GW145: =IF(ISNA(VLOOKUP(GW$3&$C145,'all-data'!$B$2:$B$7345,1,FALSE)),"",GW$3&$C145)

Sheet list-countries
B1: Country | C1: Country Code | D1: Number of Indicators Available
B2: Afghanistan | C2: AFG | D2: =COUNTIF('all-data'!E$2:E$7345,C2) -> 20
B3: Albania | C3: ALB | D3: =COUNTIF('all-data'!E$2:E$7345,C3) -> 44
B4: Algeria | C4: DZA | D4: =COUNTIF('all-data'!E$2:E$7345,C4) -> 31
B5: Andorra | C5: AND | D5: =COUNTIF('all-data'!E$2:E$7345,C5) -> 1
B6: Angola | C6: AGO | D6: =COUNTIF('all-data'!E$2:E$7345,C6) -> 26
B7: Antigua and Barbuda | C7: ATG | D7: =COUNTIF('all-data'!E$2:E$7345,C7) -> 3
B8: Argentina | C8: ARG | D8: =COUNTIF('all-data'!E$2:E$7345,C8) -> 60
B9: Armenia | C9: ARM | D9: =COUNTIF('all-data'!E$2:E$7345,C9) -> 39
B10: Aruba | C10: ABW | D10: =COUNTIF('all-data'!E$2:E$7345,C10) -> 9
B11: Australia | C11: AUS | D11: =COUNTIF('all-data'!E$2:E$7345,C11) -> 87
B12: Austria | C12: AUT | D12: =COUNTIF('all-data'!E$2:E$7345,C12) -> 72
B13: Azerbaijan | C13: AZE | D13: =COUNTIF('all-data'!E$2:E$7345,C13) -> 27
... B203: Zimbabwe | C203: ZWE | D203: =COUNTIF('all-data'!E$2:E$7345,C203) -> 20

Sheet list-indicators
A1: Indicator | B1: Indicator Code
A2: Adp Employment Change | B2: ADP
A3: New Yuan Loans | B3: BBS
A4: Business Confidence | B4: BCONF
A5: Purchasing Managers Index (PMI) | B5: BCONF
A6: Business Inventories | B6: BI
A7: Prime Lending Rate | B7: BLR
A8: Bank Lending Rate | B8: BLR
A9: Interest Rate on Collateralized Loans | B9: BLR
A10: Clearing Banks Prime Rate | B10: BLR
A11: Bank Prime Rate | B11: BLR
A12: Long Term Prime Rate | B12: BLR
... A293: Zew Economic Sentiment Index | B293: ZEW

Sheet list-sources
B1: Source | C1: URL
B2: Adimark GfK | C2: http://www.adimark.cl/es/index.asp
B3: Administration des Contributions Directes | C3: http://www.impotsdirects.public.lu/
B4: Administrative office of the U.S. Courts | C4: http://www.uscourts.gov/FederalCourts/UnderstandingtheFederalCourts/Administrativeoffice.aspx
B5: AFDB | C5: http://www.afdb.org/en/
B6: Afghanistan Revenue Department | C6: http://www.ard.gov.af/
B7: African Development Bank | C7: http://www.afdb.org/en/
B8: African Economic Outlook | C8: http://www.africaneconomicoutlook.org/en/
B9: Afristat | C9: http://www.afristat.org/
B10: Agencia Tributaria | C10: http://www.agenciatributaria.es/AEAT.internet/en_gb/Inicio.shtml
B11: Agency of Statistics of the Republic of Kazakhstan | C11: http://kyzylorda-stat.kz/eng/
B12: Albanian Taxation office | C12: http://www.tatime.gov.al/en-us/Pages/default.aspx
... B38: Autoridad de Impugnacin Tributaria (AIT), Bolivia | C38: http://www.ait.gob.bo/
B39: Autoridade Tributria
B40: Autoridade Tributria de Moambique | C40: http://www.at.gov.mz/
B41: Autoridade Tributria e Aduaneira | C41: nancas.gov.pt/at/html/index.html
B42: Autoriti Monetari Brunei Darussalam | C42: http://www.mof.gov.bn/mof/en/sections/bcmb/
B43: Bahamas Department of Statistics | C43: http://statistics.bahamas.gov.bs/
B44: Bahrain Bourse | C44: http://www.bahrainbourse.com/bhb/default.asp?language=en
B45: Banca D'italia | C45: http://www.bancaditalia.it/;internal&action=_setlanguage.action?LANGUAGE=en
B46: Banco Central de Bolivia | C46: http://www.bcb.gob.bo/
B47: Banco Central de Chile | C47: http://www.bcentral.cl/eng/index.asp
B48: Banco Central de Costa Rica | C48: http://www.bccr.fi.cr/
B49: Banco Central de Honduras | C49: http://www.bch.hn/eng/index.php
B50: Banco Central de la Repblica Argentina | C50: http://www.bcra.gov.ar/
B51: Banco Central de Nicaragua | C51: http://www.bcn.gob.ni/en/index.php
... B126: Bureau for Economic Research (BER) | C126: http://www.ber.ac.za/
B127: Bureau of Internal Revenue
B128: Bureau of Statistics and Census Libya | C128: http://bsc.ly/
B129: Bureau of the Treasury, Philippines | C129: http://www.treasury.gov.ph/
B130: Bureau of Trade and Economic Indices, Thailand | C130: http://www.price.moc.go.th/price_e/
B131: Business New Zealand | C131: http://www.businessnz.org.nz/
B132: Cabinet office, Japan | C132: http://www.cao.go.jp/index-e.html
B133: Canada Mortgage And Housing Corporation | C133: https://www.cmhc-schl.gc.ca/
B134: Canada Revenue Agency | C134: http://www.cra-arc.gc.ca/menu-eng.html
B135: Capacent | C135: http://www.capacent.com/
B136: CAPMAS, Egypt | C136: http://www.capmas.gov.eg/
B137: Caracas Stock Exchange | C137: http://www.caracasstock.com/esp/index.jsp
B138: Caribbean Centre for Money and Finance | C138: http://www.ccmf-uwi.org/
B139: Casablanca Stock Exchange | C139: http://www.casablanca-bourse.com/bourseweb/en/index.aspx
B140: Cayman Islands - The Economics & Statistics office | C140: http://www.eso.ky/
B141: CBI
B142: CBI, UK | C142: http://www.cbi.org.uk/
B143: Census and Statistics Department, Hong Kong | C143: http://www.censtatd.gov.hk/home/
B144: Cental Bank of Kosovo | C144: http://www.bqk-kos.org/?cid=2
B145: Central Administration of Statistics, Republic of Lebanon | C145: http://www.cas.gov.lb/
B146: Central Agency for Public Mobilization and Statistics | C146: http://www.capmas.gov.eg/?lang=2
B147: Central American Monetary Council | C147: http://www.centralamericadata.com/en/search?q1=content_en_le:%22Central+American+Monetary+Council%22
B148: Central Bank of Argentina | C148: http://www.bcra.gov.ar/index_i.htm
B149: Central Bank of Armenia | C149: https://www.cba.am/en/sitepages/default.aspx
B150: Central Bank of Bahrain | C150: http://www.cbb.gov.bh/
B151: Central Bank of Barbados | C151: http://www.centralbank.org.bb/
B152: Central Bank of Belize | C152: https://www.centralbank.org.bz/
B153: Central Bank of Bosnia and Herzegovina | C153: http://www.cbbh.ba/?lang=en
... B228: Central Statistics Organization, Afghanistan (CSO) | C228: http://cso.gov.af/en
B229: Central Statistics Organization, Myanmar
B230: Centrale Bank van Aruba | C230: http://www.cbaruba.org/cba/home.do
B231: Centre for European Economic Research (ZEW) | C231: http://www.zew.de/en/
B232: Centre for Monitoring Indian Economy | C232: http://www.cmie.com/
B233: Ceylon Tourist Board | C233: http://www.srilanka.travel/
B234: Challenger, Gray and Christmas, Inc. | C234: http://www.challengergray.com/
B235: Chilean Tax Administration
B236: China Association of Automobile Manufacturers | C236: http://www.caam.org.cn/english/
B237: CIA World Factbook | C237: https://www.cia.gov/library/publications/the-world-factbook/
B238: CNSEE, Congo | C238: http://www.cnsee.org/
B239: Cntl. Bank Van Curacao En Sint Maarten | C239: http://www.centralbank.an/
B240: Colombia Stock Exchange | C240: http://www.bvc.com.co/pps/tibco/portalbvc
B241: Colombo Stock Exchange | C241: http://www.cse.lk/home.do
B242: Commisioner of Inland Revenue
B243: Commissioner of Income Tax
B244: Confederacao Nacional da Industria (CNI) | C244: http://www.portaldaindustria.com.br/
B245: Confederation of British Industry | C245: http://www.cbi.org.uk/
B246: Confederation of Indian Industry (CII) | C246: http://www.cii.in/
B247: Consejo Monetario Centro Americano | C247: http://www.secmca.org/
B248: Controller General of Accounts, India | C248: http://www.cga.nic.in/
B249: Copenhagen Stock Exchange | C249: http://www.nasdaqomxnordic.com/news/marketnotices/copenhagen
B250: Council of Labour Affairs | C250: http://english.mol.gov.tw/cgi-bin/siteMaker/SM_theme?page=52f34260
B251: Croatian Bureau of Statistics | C251: http://www.dzs.hr/default_e.htm
B252: Croatian National Bank | C252: http://www.hnb.hr/eindex.htm
B253: Customs and Inland Revenue
B254: Cyprus Stock Exchange | C254: http://www.cse.com.cy/en-GB/home/
B255: Czech National Bank | C255: https://www.cnb.cz/en/
B256: Czech Social Security Administration | C256: http://www.cssz.cz/en/about-cssa/
B257: Czech Statistical office | C257: http://www.czso.cz/eng/redakce.nsf/i/home
B258: Da Afghanistan Bank | C258: http://www.centralbank.gov.af/index.php
B259: Dane, Colombia | C259: https://www.dane.gov.co/
B260: Danish Central Tax Administration | C260: http://www.skm.dk/
B261: Danmarks Nationalbank | C261: http://www.nationalbanken.dk/en/Pages/default.aspx
B262: De Nederlandsche Bank | C262: http://www.dnb.nl/en/home/
B263: Decima Research Inc. | C263: http://www.harrisdecima.ca/
B264: Department of Census and Statistics - Sri Lanka | C264: http://www.statistics.gov.lk/
B265: Department of Economic Planning and Development, Brunei | C265: http://www.depd.gov.bn/home.html
B266: Department of Finance and Economy
B267: Department of Finance Canada | C267: http://www.fin.gc.ca/fin-eng.asp
B268: Department of Finance of the Philippine Republic | C268: http://www.dof.gov.ph/
B269: Department of Income Tax
B270: Department of Land Transport, Thailand | C270: http://driving.information.in.th/thai-dmv.html
B271: Department of National Planning, Republic of Maldives | C271: http://www.planning.gov.mv/en/
B272: Department of Public Revenues, Montenegro | C272: http://www.poreskauprava.gov.me/en/administration
B273: Department of Revenue and Customs
...
